blossom/__init__.py
blossom/conf/__init__.py
blossom/conf/config.py
blossom/context/__init__.py
blossom/context/context.py
blossom/context/provider_manager.py
blossom/dataframe/__init__.py
blossom/dataframe/aggregate.py
blossom/dataframe/data_handler.py
blossom/dataframe/dataframe.py
blossom/dataframe/local_dataframe.py
blossom/dataframe/multiprocess_dataframe.py
blossom/dataframe/ray_dataframe.py
blossom/dataframe/spark_dataframe.py
blossom/dataset/AGENTS.md
blossom/dataset/__init__.py
blossom/dataset/dataset.py
blossom/dataset/loader.py
blossom/dataset/standard_dataset.py
blossom/log.py
blossom/op/AGENTS.md
blossom/op/__init__.py
blossom/op/chat/chat_content_filter.py
blossom/op/chat/chat_content_replacer.py
blossom/op/chat/chat_content_trimmer.py
blossom/op/chat/chat_context_round_trimmer.py
blossom/op/chat/chat_conversation_synthesizer.py
blossom/op/chat/chat_distiller.py
blossom/op/chat/chat_embedder.py
blossom/op/chat/chat_invalid_filter.py
blossom/op/chat/chat_length_filter.py
blossom/op/chat/chat_reasoning_consistency_filter.py
blossom/op/chat/chat_reasoning_content_merger.py
blossom/op/chat/chat_repetition_filter.py
blossom/op/chat/chat_translator.py
blossom/op/chat/chat_verify_distiller.py
blossom/op/common/equal_width_binner.py
blossom/op/common/llm_judge_filter.py
blossom/op/common/metadata_clearer.py
blossom/op/failed_item_filter.py
blossom/op/filter_operator.py
blossom/op/map_operator.py
blossom/op/metric_filter_operator.py
blossom/op/operator.py
blossom/op/text/text_content_filter.py
blossom/op/text/text_content_replacer.py
blossom/op/text/text_embedder.py
blossom/op/text/text_length_filter.py
blossom/op/text/text_repetition_filter.py
blossom/op/text/text_translator.py
blossom/op/text/text_trimmer.py
blossom/op/transform_operator.py
blossom/op/util/char_repetition_filter.py
blossom/op/util/content_embedder.py
blossom/op/util/content_translator.py
blossom/provider/__init__.py
blossom/provider/openai.py
blossom/provider/protocol.py
blossom_data-0.5.1.dist-info/METADATA
blossom_data-0.5.1.dist-info/WHEEL
blossom_data-0.5.1.dist-info/licenses/LICENSE
blossom_data-0.5.1.dist-info/RECORD
