Metadata-Version: 2.4
Name: blossom-data
Version: 0.5.1
Summary: A simple way to synthesize LLM training data.
License: MIT
License-File: LICENSE
Keywords: llm,data synthesis,data processing,pyspark,ray,machine learning,nlp
Author: Azure99
Requires-Python: >=3.9,<4.0
Classifier: License :: OSI Approved :: MIT License
Classifier: Programming Language :: Python :: 3
Classifier: Programming Language :: Python :: 3.9
Classifier: Programming Language :: Python :: 3.10
Classifier: Programming Language :: Python :: 3.11
Classifier: Programming Language :: Python :: 3.12
Classifier: Programming Language :: Python :: 3.13
Classifier: Programming Language :: Python :: 3.14
Requires-Dist: cloudpickle (>=3.0,<4.0)
Requires-Dist: numpy (>=2.0,<3.0)
Requires-Dist: pillow (>=10.0,<11.0)
Requires-Dist: pyarrow (>=15.0.0)
Requires-Dist: pydantic (>=2.0,<3.0)
Requires-Dist: pyspark (>=3.0,<4.0)
Requires-Dist: pyyaml (>=6.0,<7.0)
Requires-Dist: ray[data] (>=2.0,<3.0)
Requires-Dist: requests (>=2.0,<3.0)
Project-URL: Repository, https://github.com/Azure99/BlossomData
